flammkuchen/__init__.py
flammkuchen/conf.py
flammkuchen/hdf5io.py
flammkuchen/ls.py
flammkuchen-1.0.3.dist-info/LICENSE
flammkuchen-1.0.3.dist-info/METADATA
flammkuchen-1.0.3.dist-info/WHEEL
flammkuchen-1.0.3.dist-info/top_level.txt
flammkuchen-1.0.3.dist-info/RECORD
